pyee2/__init__.py
pyee2/eventemitter.py
pyee2/eventemitterS.py
pyee2-2.0.0.dist-info/METADATA
pyee2-2.0.0.dist-info/WHEEL
pyee2-2.0.0.dist-info/top_level.txt
pyee2-2.0.0.dist-info/RECORD
