Metadata-Version: 2.1
Name: pyee2
Version: 2.0.0
Summary: A port of node.js's primus/eventemitter3 to python. Based on jfhbrook/pyee.
Home-page: https://github.com/N0taN3rd/pyee2
Author: John Berlin
Author-email: n0tan3rd@gmail.com
License: MIT
Keywords: events,emitter,node.js,node,eventemitter,eventemitter3
Platform: UNKNOWN
Classifier: Programming Language :: Python
Classifier: Development Status :: 4 - Beta
Classifier: Intended Audience :: Developers
Classifier: License :: OSI Approved :: MIT License
Classifier: Operating System :: OS Independent
Classifier: Programming Language :: Python
Classifier: Programming Language :: Python :: 3.5
Classifier: Programming Language :: Python :: 3.6
Classifier: Programming Language :: Python :: 3.7
Classifier: Topic :: Other/Nonlisted Topic
Requires-Python: >= 3.5
